<?xml version="1.0" encoding="UTF-8"?>
<character>
  <utf8>辥</utf8>
  <width>1000</width>
  <height>1000</height>
  <strokes>
    <stroke>
      <point x="176" y="213" timestamp="0" />
      <point x="176" y="213" timestamp="8" />
      <point x="176" y="213" timestamp="16" />
      <point x="176" y="213" timestamp="32" />
      <point x="176" y="213" timestamp="40" />
      <point x="176" y="213" timestamp="48" />
      <point x="176" y="213" timestamp="56" />
      <point x="176" y="213" timestamp="72" />
      <point x="176" y="213" timestamp="80" />
      <point x="176" y="213" timestamp="112" />
      <point x="176" y="213" timestamp="120" />
      <point x="176" y="213" timestamp="128" />
      <point x="176" y="216" timestamp="152" />
      <point x="176" y="220" timestamp="160" />
      <point x="176" y="226" timestamp="176" />
      <point x="176" y="233" timestamp="192" />
      <point x="176" y="240" timestamp="200" />
      <point x="176" y="246" timestamp="208" />
      <point x="176" y="253" timestamp="232" />
      <point x="176" y="256" timestamp="240" />
      <point x="176" y="263" timestamp="264" />
      <point x="176" y="270" timestamp="280" />
      <point x="176" y="273" timestamp="288" />
      <point x="176" y="280" timestamp="312" />
      <point x="176" y="286" timestamp="320" />
      <point x="170" y="293" timestamp="344" />
      <point x="170" y="293" timestamp="376" />
      <point x="170" y="296" timestamp="384" />
      <point x="170" y="296" timestamp="392" />
      <point x="170" y="296" timestamp="400" />
      <point x="170" y="296" timestamp="432" />
      <point x="170" y="296" timestamp="488" />
      <point x="170" y="296" timestamp="536" />
      <point x="170" y="300" timestamp="552" />
      <point x="170" y="300" timestamp="616" />
      <point x="170" y="300" timestamp="624" />
      <point x="170" y="300" timestamp="640" />
      <point x="170" y="300" timestamp="656" />
      <point x="170" y="300" timestamp="664" />
      <point x="173" y="300" timestamp="696" />
      <point x="176" y="300" timestamp="704" />
      <point x="183" y="300" timestamp="720" />
      <point x="190" y="300" timestamp="728" />
      <point x="196" y="300" timestamp="736" />
      <point x="206" y="300" timestamp="752" />
      <point x="213" y="300" timestamp="760" />
      <point x="226" y="300" timestamp="768" />
      <point x="233" y="300" timestamp="776" />
      <point x="246" y="300" timestamp="792" />
      <point x="256" y="300" timestamp="800" />
      <point x="270" y="300" timestamp="808" />
      <point x="283" y="300" timestamp="816" />
      <point x="290" y="293" timestamp="832" />
      <point x="303" y="293" timestamp="840" />
      <point x="310" y="293" timestamp="848" />
      <point x="320" y="293" timestamp="856" />
      <point x="326" y="293" timestamp="872" />
      <point x="340" y="293" timestamp="880" />
      <point x="346" y="293" timestamp="888" />
      <point x="353" y="293" timestamp="904" />
      <point x="363" y="293" timestamp="912" />
      <point x="370" y="293" timestamp="920" />
      <point x="376" y="293" timestamp="928" />
      <point x="390" y="293" timestamp="944" />
      <point x="396" y="293" timestamp="952" />
      <point x="400" y="293" timestamp="960" />
      <point x="413" y="293" timestamp="968" />
      <point x="420" y="293" timestamp="992" />
      <point x="426" y="293" timestamp="1000" />
      <point x="430" y="293" timestamp="1016" />
      <point x="436" y="293" timestamp="1024" />
      <point x="436" y="293" timestamp="1032" />
      <point x="443" y="293" timestamp="1040" />
      <point x="450" y="293" timestamp="1056" />
      <point x="453" y="293" timestamp="1080" />
      <point x="453" y="300" timestamp="1096" />
      <point x="453" y="300" timestamp="1104" />
      <point x="453" y="300" timestamp="1112" />
    </stroke>
    <stroke>
      <point x="430" y="210" timestamp="1424" />
      <point x="430" y="210" timestamp="1440" />
      <point x="430" y="210" timestamp="1448" />
      <point x="430" y="210" timestamp="1464" />
      <point x="430" y="210" timestamp="1480" />
      <point x="430" y="210" timestamp="1488" />
      <point x="430" y="213" timestamp="1496" />
      <point x="430" y="216" timestamp="1512" />
      <point x="430" y="223" timestamp="1520" />
      <point x="430" y="236" timestamp="1528" />
      <point x="430" y="243" timestamp="1536" />
      <point x="430" y="256" timestamp="1552" />
      <point x="430" y="266" timestamp="1560" />
      <point x="430" y="273" timestamp="1568" />
      <point x="430" y="280" timestamp="1576" />
      <point x="436" y="286" timestamp="1592" />
      <point x="436" y="293" timestamp="1600" />
      <point x="436" y="293" timestamp="1608" />
      <point x="436" y="293" timestamp="1624" />
    </stroke>
    <stroke>
      <point x="310" y="153" timestamp="2088" />
      <point x="310" y="153" timestamp="2096" />
      <point x="310" y="153" timestamp="2104" />
      <point x="310" y="153" timestamp="2120" />
      <point x="310" y="153" timestamp="2128" />
      <point x="310" y="153" timestamp="2136" />
      <point x="310" y="153" timestamp="2144" />
      <point x="310" y="156" timestamp="2160" />
      <point x="310" y="160" timestamp="2168" />
      <point x="310" y="166" timestamp="2176" />
      <point x="310" y="173" timestamp="2184" />
      <point x="303" y="180" timestamp="2200" />
      <point x="303" y="186" timestamp="2208" />
      <point x="303" y="193" timestamp="2217" />
      <point x="296" y="206" timestamp="2232" />
      <point x="296" y="213" timestamp="2240" />
      <point x="290" y="216" timestamp="2248" />
      <point x="290" y="230" timestamp="2256" />
      <point x="290" y="236" timestamp="2272" />
      <point x="283" y="243" timestamp="2280" />
      <point x="283" y="250" timestamp="2289" />
      <point x="276" y="256" timestamp="2296" />
      <point x="276" y="263" timestamp="2312" />
      <point x="270" y="273" timestamp="2320" />
      <point x="270" y="280" timestamp="2329" />
      <point x="266" y="286" timestamp="2344" />
      <point x="266" y="293" timestamp="2352" />
      <point x="260" y="300" timestamp="2360" />
      <point x="260" y="306" timestamp="2368" />
      <point x="253" y="313" timestamp="2384" />
      <point x="253" y="323" timestamp="2392" />
      <point x="246" y="330" timestamp="2401" />
      <point x="240" y="336" timestamp="2408" />
      <point x="240" y="343" timestamp="2424" />
      <point x="233" y="350" timestamp="2432" />
      <point x="226" y="356" timestamp="2441" />
      <point x="220" y="363" timestamp="2448" />
      <point x="213" y="366" timestamp="2464" />
      <point x="206" y="373" timestamp="2480" />
      <point x="200" y="380" timestamp="2496" />
      <point x="193" y="386" timestamp="2504" />
      <point x="193" y="393" timestamp="2512" />
      <point x="186" y="400" timestamp="2520" />
      <point x="180" y="406" timestamp="2536" />
      <point x="173" y="406" timestamp="2552" />
      <point x="173" y="410" timestamp="2560" />
      <point x="173" y="410" timestamp="2576" />
      <point x="173" y="410" timestamp="2584" />
      <point x="173" y="410" timestamp="2592" />
      <point x="173" y="410" timestamp="2601" />
    </stroke>
    <stroke>
      <point x="296" y="340" timestamp="4040" />
      <point x="300" y="340" timestamp="4056" />
      <point x="300" y="340" timestamp="4064" />
      <point x="300" y="340" timestamp="4072" />
      <point x="300" y="340" timestamp="4104" />
      <point x="300" y="343" timestamp="4112" />
      <point x="300" y="343" timestamp="4128" />
      <point x="296" y="346" timestamp="4136" />
      <point x="293" y="350" timestamp="4144" />
      <point x="286" y="356" timestamp="4152" />
      <point x="280" y="356" timestamp="4168" />
      <point x="273" y="363" timestamp="4176" />
      <point x="273" y="370" timestamp="4184" />
      <point x="266" y="376" timestamp="4192" />
      <point x="266" y="376" timestamp="4208" />
    </stroke>
    <stroke>
      <point x="213" y="403" timestamp="4632" />
      <point x="213" y="403" timestamp="4640" />
      <point x="213" y="403" timestamp="4648" />
      <point x="210" y="403" timestamp="4664" />
      <point x="210" y="403" timestamp="4672" />
      <point x="210" y="403" timestamp="4680" />
      <point x="210" y="403" timestamp="4696" />
      <point x="210" y="403" timestamp="4704" />
      <point x="213" y="403" timestamp="4712" />
      <point x="213" y="410" timestamp="4720" />
      <point x="216" y="410" timestamp="4736" />
      <point x="223" y="410" timestamp="4744" />
      <point x="230" y="410" timestamp="4752" />
      <point x="236" y="410" timestamp="4760" />
      <point x="243" y="410" timestamp="4776" />
      <point x="246" y="410" timestamp="4784" />
      <point x="253" y="410" timestamp="4792" />
      <point x="260" y="410" timestamp="4800" />
      <point x="266" y="410" timestamp="4816" />
      <point x="273" y="410" timestamp="4824" />
      <point x="276" y="410" timestamp="4832" />
      <point x="283" y="410" timestamp="4848" />
      <point x="296" y="410" timestamp="4856" />
      <point x="303" y="410" timestamp="4864" />
      <point x="310" y="410" timestamp="4872" />
      <point x="320" y="410" timestamp="4888" />
      <point x="326" y="410" timestamp="4896" />
      <point x="340" y="410" timestamp="4904" />
      <point x="346" y="410" timestamp="4912" />
      <point x="353" y="410" timestamp="4928" />
      <point x="363" y="403" timestamp="4936" />
      <point x="370" y="403" timestamp="4944" />
      <point x="376" y="403" timestamp="4952" />
      <point x="383" y="403" timestamp="4968" />
      <point x="393" y="396" timestamp="4976" />
      <point x="400" y="396" timestamp="4985" />
      <point x="406" y="396" timestamp="5000" />
      <point x="413" y="396" timestamp="5008" />
      <point x="420" y="396" timestamp="5040" />
      <point x="420" y="396" timestamp="5064" />
      <point x="420" y="400" timestamp="5088" />
      <point x="420" y="403" timestamp="5096" />
      <point x="420" y="410" timestamp="5112" />
      <point x="420" y="416" timestamp="5120" />
      <point x="420" y="423" timestamp="5128" />
      <point x="420" y="430" timestamp="5136" />
      <point x="420" y="443" timestamp="5152" />
      <point x="413" y="450" timestamp="5160" />
      <point x="413" y="460" timestamp="5168" />
      <point x="413" y="466" timestamp="5176" />
      <point x="413" y="480" timestamp="5192" />
      <point x="413" y="486" timestamp="5200" />
      <point x="413" y="493" timestamp="5208" />
      <point x="413" y="506" timestamp="5216" />
      <point x="413" y="513" timestamp="5232" />
      <point x="413" y="516" timestamp="5240" />
      <point x="413" y="523" timestamp="5248" />
      <point x="413" y="523" timestamp="5272" />
      <point x="413" y="523" timestamp="5280" />
      <point x="413" y="530" timestamp="5288" />
      <point x="413" y="530" timestamp="5304" />
    </stroke>
    <stroke>
      <point x="216" y="553" timestamp="5648" />
      <point x="216" y="553" timestamp="5656" />
      <point x="216" y="553" timestamp="5664" />
      <point x="216" y="553" timestamp="5672" />
      <point x="216" y="553" timestamp="5688" />
      <point x="216" y="553" timestamp="5696" />
      <point x="216" y="553" timestamp="5704" />
      <point x="216" y="553" timestamp="5720" />
      <point x="216" y="553" timestamp="5728" />
      <point x="220" y="553" timestamp="5736" />
      <point x="223" y="553" timestamp="5744" />
      <point x="236" y="553" timestamp="5760" />
      <point x="250" y="553" timestamp="5768" />
      <point x="266" y="553" timestamp="5776" />
      <point x="280" y="546" timestamp="5784" />
      <point x="300" y="546" timestamp="5800" />
      <point x="316" y="546" timestamp="5808" />
      <point x="330" y="540" timestamp="5817" />
      <point x="343" y="540" timestamp="5824" />
      <point x="356" y="540" timestamp="5840" />
      <point x="363" y="540" timestamp="5848" />
      <point x="370" y="540" timestamp="5856" />
      <point x="373" y="540" timestamp="5880" />
      <point x="373" y="540" timestamp="5896" />
      <point x="373" y="540" timestamp="5912" />
      <point x="373" y="540" timestamp="5920" />
    </stroke>
    <stroke>
      <point x="190" y="426" timestamp="6368" />
      <point x="190" y="426" timestamp="6376" />
      <point x="190" y="426" timestamp="6384" />
      <point x="190" y="426" timestamp="6392" />
      <point x="190" y="426" timestamp="6408" />
      <point x="190" y="430" timestamp="6416" />
      <point x="190" y="436" timestamp="6424" />
      <point x="190" y="440" timestamp="6440" />
      <point x="190" y="453" timestamp="6448" />
      <point x="190" y="460" timestamp="6456" />
      <point x="190" y="473" timestamp="6464" />
      <point x="190" y="486" timestamp="6480" />
      <point x="190" y="500" timestamp="6488" />
      <point x="190" y="513" timestamp="6496" />
      <point x="190" y="526" timestamp="6504" />
      <point x="190" y="540" timestamp="6520" />
      <point x="190" y="553" timestamp="6528" />
      <point x="190" y="560" timestamp="6536" />
      <point x="190" y="570" timestamp="6544" />
      <point x="193" y="583" timestamp="6560" />
      <point x="193" y="590" timestamp="6568" />
      <point x="193" y="603" timestamp="6576" />
      <point x="193" y="610" timestamp="6592" />
      <point x="193" y="623" timestamp="6600" />
      <point x="193" y="636" timestamp="6608" />
      <point x="200" y="643" timestamp="6616" />
      <point x="200" y="646" timestamp="6632" />
      <point x="200" y="660" timestamp="6640" />
      <point x="200" y="666" timestamp="6648" />
      <point x="200" y="680" timestamp="6656" />
      <point x="200" y="686" timestamp="6672" />
      <point x="200" y="700" timestamp="6680" />
      <point x="206" y="713" timestamp="6688" />
      <point x="206" y="720" timestamp="6704" />
      <point x="206" y="723" timestamp="6712" />
      <point x="206" y="730" timestamp="6720" />
      <point x="206" y="736" timestamp="6729" />
      <point x="206" y="743" timestamp="6744" />
      <point x="206" y="750" timestamp="6752" />
      <point x="206" y="756" timestamp="6760" />
      <point x="206" y="760" timestamp="6768" />
      <point x="206" y="766" timestamp="6784" />
      <point x="206" y="773" timestamp="6792" />
      <point x="206" y="780" timestamp="6800" />
      <point x="206" y="780" timestamp="6808" />
      <point x="206" y="786" timestamp="6824" />
      <point x="206" y="786" timestamp="6832" />
      <point x="206" y="786" timestamp="6840" />
    </stroke>
    <stroke>
      <point x="196" y="613" timestamp="7200" />
      <point x="196" y="613" timestamp="7208" />
      <point x="193" y="613" timestamp="7216" />
      <point x="193" y="613" timestamp="7224" />
      <point x="193" y="613" timestamp="7240" />
      <point x="193" y="613" timestamp="7248" />
      <point x="193" y="613" timestamp="7256" />
      <point x="193" y="613" timestamp="7264" />
      <point x="193" y="613" timestamp="7280" />
      <point x="193" y="613" timestamp="7288" />
      <point x="196" y="613" timestamp="7296" />
      <point x="203" y="613" timestamp="7304" />
      <point x="206" y="613" timestamp="7320" />
      <point x="213" y="613" timestamp="7328" />
      <point x="220" y="613" timestamp="7336" />
      <point x="226" y="613" timestamp="7352" />
      <point x="233" y="613" timestamp="7360" />
      <point x="243" y="613" timestamp="7368" />
      <point x="250" y="613" timestamp="7376" />
      <point x="263" y="613" timestamp="7392" />
      <point x="270" y="613" timestamp="7400" />
      <point x="283" y="613" timestamp="7408" />
      <point x="286" y="613" timestamp="7416" />
      <point x="293" y="613" timestamp="7432" />
      <point x="300" y="613" timestamp="7440" />
      <point x="306" y="613" timestamp="7448" />
      <point x="316" y="613" timestamp="7464" />
      <point x="323" y="613" timestamp="7472" />
      <point x="336" y="613" timestamp="7480" />
      <point x="343" y="613" timestamp="7488" />
      <point x="350" y="613" timestamp="7504" />
      <point x="356" y="613" timestamp="7512" />
      <point x="360" y="613" timestamp="7520" />
      <point x="366" y="613" timestamp="7528" />
      <point x="373" y="613" timestamp="7552" />
      <point x="376" y="613" timestamp="7560" />
      <point x="383" y="613" timestamp="7568" />
      <point x="390" y="613" timestamp="7592" />
      <point x="393" y="613" timestamp="7600" />
      <point x="400" y="620" timestamp="7664" />
      <point x="400" y="623" timestamp="7680" />
      <point x="400" y="626" timestamp="7696" />
      <point x="400" y="626" timestamp="7704" />
      <point x="400" y="633" timestamp="7712" />
      <point x="400" y="636" timestamp="7720" />
      <point x="400" y="650" timestamp="7736" />
      <point x="400" y="656" timestamp="7744" />
      <point x="400" y="663" timestamp="7752" />
      <point x="400" y="676" timestamp="7768" />
      <point x="400" y="683" timestamp="7776" />
      <point x="400" y="696" timestamp="7784" />
      <point x="400" y="703" timestamp="7792" />
      <point x="400" y="706" timestamp="7808" />
      <point x="400" y="713" timestamp="7824" />
      <point x="400" y="713" timestamp="7832" />
      <point x="400" y="716" timestamp="7848" />
      <point x="400" y="716" timestamp="7856" />
      <point x="400" y="716" timestamp="7864" />
    </stroke>
    <stroke>
      <point x="210" y="746" timestamp="8264" />
      <point x="210" y="746" timestamp="8272" />
      <point x="210" y="746" timestamp="8280" />
      <point x="210" y="746" timestamp="8288" />
      <point x="210" y="746" timestamp="8304" />
      <point x="210" y="746" timestamp="8312" />
      <point x="210" y="746" timestamp="8320" />
      <point x="210" y="746" timestamp="8336" />
      <point x="210" y="746" timestamp="8344" />
      <point x="210" y="746" timestamp="8352" />
      <point x="210" y="746" timestamp="8360" />
      <point x="210" y="746" timestamp="8376" />
      <point x="210" y="746" timestamp="8384" />
      <point x="213" y="746" timestamp="8392" />
      <point x="220" y="746" timestamp="8400" />
      <point x="223" y="746" timestamp="8416" />
      <point x="230" y="746" timestamp="8424" />
      <point x="243" y="746" timestamp="8432" />
      <point x="250" y="746" timestamp="8448" />
      <point x="260" y="746" timestamp="8456" />
      <point x="266" y="746" timestamp="8464" />
      <point x="280" y="746" timestamp="8472" />
      <point x="286" y="746" timestamp="8488" />
      <point x="296" y="746" timestamp="8496" />
      <point x="303" y="746" timestamp="8504" />
      <point x="316" y="740" timestamp="8512" />
      <point x="323" y="740" timestamp="8528" />
      <point x="330" y="740" timestamp="8536" />
      <point x="333" y="740" timestamp="8544" />
      <point x="340" y="740" timestamp="8552" />
      <point x="346" y="740" timestamp="8568" />
      <point x="353" y="740" timestamp="8576" />
      <point x="360" y="740" timestamp="8584" />
      <point x="363" y="740" timestamp="8592" />
      <point x="370" y="733" timestamp="8608" />
      <point x="376" y="733" timestamp="8624" />
      <point x="383" y="733" timestamp="8640" />
      <point x="386" y="733" timestamp="8648" />
      <point x="393" y="733" timestamp="8656" />
      <point x="400" y="733" timestamp="8680" />
      <point x="406" y="733" timestamp="8696" />
      <point x="406" y="733" timestamp="8728" />
      <point x="406" y="733" timestamp="8736" />
      <point x="406" y="733" timestamp="8744" />
      <point x="410" y="733" timestamp="8760" />
      <point x="410" y="733" timestamp="8768" />
      <point x="410" y="733" timestamp="8776" />
      <point x="410" y="733" timestamp="8792" />
      <point x="410" y="726" timestamp="8800" />
    </stroke>
    <stroke>
      <point x="643" y="146" timestamp="10056" />
      <point x="643" y="146" timestamp="10072" />
      <point x="643" y="146" timestamp="10080" />
      <point x="643" y="146" timestamp="10088" />
      <point x="643" y="146" timestamp="10112" />
      <point x="643" y="146" timestamp="10120" />
      <point x="643" y="146" timestamp="10128" />
      <point x="643" y="153" timestamp="10136" />
      <point x="646" y="156" timestamp="10152" />
      <point x="646" y="170" timestamp="10160" />
      <point x="646" y="183" timestamp="10169" />
      <point x="653" y="196" timestamp="10184" />
      <point x="653" y="203" timestamp="10192" />
      <point x="660" y="216" timestamp="10200" />
      <point x="660" y="220" timestamp="10208" />
      <point x="660" y="226" timestamp="10224" />
      <point x="660" y="226" timestamp="10232" />
      <point x="660" y="226" timestamp="10240" />
    </stroke>
    <stroke>
      <point x="503" y="263" timestamp="10696" />
      <point x="503" y="263" timestamp="10704" />
      <point x="503" y="263" timestamp="10720" />
      <point x="503" y="263" timestamp="10728" />
      <point x="503" y="263" timestamp="10736" />
      <point x="503" y="263" timestamp="10752" />
      <point x="503" y="263" timestamp="10760" />
      <point x="503" y="263" timestamp="10768" />
      <point x="503" y="263" timestamp="10776" />
      <point x="506" y="263" timestamp="10792" />
      <point x="516" y="263" timestamp="10800" />
      <point x="530" y="263" timestamp="10808" />
      <point x="543" y="263" timestamp="10816" />
      <point x="556" y="263" timestamp="10832" />
      <point x="566" y="263" timestamp="10840" />
      <point x="580" y="256" timestamp="10848" />
      <point x="593" y="256" timestamp="10856" />
      <point x="606" y="256" timestamp="10872" />
      <point x="620" y="256" timestamp="10880" />
      <point x="633" y="256" timestamp="10888" />
      <point x="643" y="256" timestamp="10904" />
      <point x="650" y="256" timestamp="10912" />
      <point x="663" y="256" timestamp="10920" />
      <point x="676" y="256" timestamp="10928" />
      <point x="690" y="256" timestamp="10944" />
      <point x="700" y="250" timestamp="10952" />
      <point x="713" y="250" timestamp="10960" />
      <point x="726" y="250" timestamp="10968" />
      <point x="740" y="250" timestamp="10984" />
      <point x="746" y="250" timestamp="10992" />
      <point x="753" y="250" timestamp="11000" />
      <point x="763" y="250" timestamp="11008" />
      <point x="770" y="250" timestamp="11024" />
      <point x="776" y="250" timestamp="11032" />
      <point x="783" y="250" timestamp="11040" />
      <point x="786" y="250" timestamp="11064" />
      <point x="793" y="250" timestamp="11072" />
      <point x="793" y="250" timestamp="11080" />
      <point x="796" y="250" timestamp="11096" />
      <point x="796" y="250" timestamp="11112" />
      <point x="796" y="250" timestamp="11120" />
      <point x="796" y="250" timestamp="11136" />
      <point x="796" y="250" timestamp="11144" />
    </stroke>
    <stroke>
      <point x="583" y="300" timestamp="11632" />
      <point x="583" y="300" timestamp="11640" />
      <point x="583" y="300" timestamp="11648" />
      <point x="583" y="303" timestamp="11664" />
      <point x="583" y="303" timestamp="11672" />
      <point x="583" y="303" timestamp="11680" />
      <point x="583" y="306" timestamp="11688" />
      <point x="586" y="313" timestamp="11704" />
      <point x="593" y="316" timestamp="11712" />
      <point x="600" y="316" timestamp="11721" />
      <point x="606" y="323" timestamp="11737" />
      <point x="606" y="330" timestamp="11744" />
      <point x="610" y="336" timestamp="11753" />
      <point x="610" y="343" timestamp="11760" />
      <point x="616" y="343" timestamp="11776" />
      <point x="616" y="350" timestamp="11784" />
    </stroke>
    <stroke>
      <point x="736" y="283" timestamp="12120" />
      <point x="736" y="283" timestamp="12128" />
      <point x="736" y="283" timestamp="12136" />
      <point x="736" y="283" timestamp="12144" />
      <point x="736" y="283" timestamp="12160" />
      <point x="736" y="286" timestamp="12168" />
      <point x="736" y="286" timestamp="12176" />
      <point x="733" y="293" timestamp="12192" />
      <point x="726" y="300" timestamp="12200" />
      <point x="720" y="303" timestamp="12208" />
      <point x="713" y="310" timestamp="12216" />
      <point x="706" y="323" timestamp="12232" />
      <point x="700" y="330" timestamp="12240" />
      <point x="693" y="336" timestamp="12248" />
      <point x="686" y="343" timestamp="12256" />
      <point x="676" y="353" timestamp="12272" />
    </stroke>
    <stroke>
      <point x="566" y="410" timestamp="13576" />
      <point x="566" y="410" timestamp="13584" />
      <point x="566" y="410" timestamp="13600" />
      <point x="563" y="410" timestamp="13608" />
      <point x="563" y="410" timestamp="13616" />
      <point x="563" y="410" timestamp="13632" />
      <point x="563" y="410" timestamp="13640" />
      <point x="563" y="410" timestamp="13649" />
      <point x="563" y="410" timestamp="13656" />
      <point x="563" y="410" timestamp="13672" />
      <point x="563" y="410" timestamp="13680" />
      <point x="563" y="410" timestamp="13689" />
      <point x="563" y="410" timestamp="13696" />
      <point x="563" y="410" timestamp="13712" />
      <point x="563" y="410" timestamp="13720" />
      <point x="563" y="410" timestamp="13729" />
      <point x="566" y="410" timestamp="13737" />
      <point x="566" y="410" timestamp="13752" />
      <point x="580" y="410" timestamp="13760" />
      <point x="593" y="410" timestamp="13768" />
      <point x="600" y="410" timestamp="13784" />
      <point x="610" y="410" timestamp="13792" />
      <point x="623" y="410" timestamp="13800" />
      <point x="636" y="410" timestamp="13809" />
      <point x="643" y="410" timestamp="13824" />
      <point x="656" y="410" timestamp="13832" />
      <point x="666" y="410" timestamp="13840" />
      <point x="680" y="410" timestamp="13849" />
      <point x="686" y="410" timestamp="13864" />
      <point x="700" y="410" timestamp="13872" />
      <point x="713" y="410" timestamp="13880" />
      <point x="723" y="410" timestamp="13896" />
      <point x="736" y="410" timestamp="13904" />
      <point x="743" y="410" timestamp="13912" />
      <point x="756" y="410" timestamp="13921" />
      <point x="763" y="410" timestamp="13936" />
      <point x="773" y="410" timestamp="13944" />
      <point x="780" y="410" timestamp="13952" />
      <point x="786" y="410" timestamp="13961" />
      <point x="793" y="410" timestamp="13976" />
      <point x="800" y="410" timestamp="13984" />
      <point x="803" y="410" timestamp="13992" />
      <point x="810" y="410" timestamp="14016" />
      <point x="816" y="410" timestamp="14024" />
      <point x="823" y="410" timestamp="14033" />
      <point x="826" y="410" timestamp="14056" />
      <point x="826" y="410" timestamp="14064" />
      <point x="826" y="410" timestamp="14073" />
      <point x="826" y="410" timestamp="14088" />
      <point x="826" y="410" timestamp="14096" />
      <point x="826" y="410" timestamp="14104" />
    </stroke>
    <stroke>
      <point x="576" y="530" timestamp="14456" />
      <point x="576" y="530" timestamp="14472" />
      <point x="576" y="530" timestamp="14480" />
      <point x="576" y="530" timestamp="14488" />
      <point x="576" y="530" timestamp="14504" />
      <point x="573" y="530" timestamp="14512" />
      <point x="573" y="530" timestamp="14520" />
      <point x="573" y="530" timestamp="14529" />
      <point x="573" y="530" timestamp="14544" />
      <point x="573" y="530" timestamp="14552" />
      <point x="570" y="530" timestamp="14560" />
      <point x="570" y="530" timestamp="14569" />
      <point x="570" y="530" timestamp="14584" />
      <point x="570" y="530" timestamp="14592" />
      <point x="570" y="530" timestamp="14600" />
      <point x="570" y="530" timestamp="14609" />
      <point x="570" y="530" timestamp="14624" />
      <point x="570" y="533" timestamp="14632" />
      <point x="570" y="533" timestamp="14640" />
      <point x="570" y="533" timestamp="14656" />
      <point x="573" y="533" timestamp="14664" />
      <point x="583" y="533" timestamp="14672" />
      <point x="596" y="533" timestamp="14681" />
      <point x="610" y="533" timestamp="14696" />
      <point x="623" y="533" timestamp="14704" />
      <point x="636" y="533" timestamp="14712" />
      <point x="653" y="533" timestamp="14721" />
      <point x="666" y="533" timestamp="14736" />
      <point x="680" y="526" timestamp="14744" />
      <point x="693" y="526" timestamp="14752" />
      <point x="706" y="526" timestamp="14760" />
      <point x="716" y="526" timestamp="14776" />
      <point x="730" y="526" timestamp="14784" />
      <point x="743" y="520" timestamp="14792" />
      <point x="756" y="520" timestamp="14808" />
      <point x="763" y="520" timestamp="14816" />
      <point x="773" y="520" timestamp="14825" />
      <point x="780" y="520" timestamp="14832" />
      <point x="786" y="520" timestamp="14848" />
      <point x="793" y="520" timestamp="14856" />
      <point x="800" y="520" timestamp="14864" />
      <point x="803" y="520" timestamp="14872" />
      <point x="810" y="520" timestamp="14920" />
      <point x="810" y="520" timestamp="14928" />
      <point x="810" y="520" timestamp="14936" />
      <point x="810" y="520" timestamp="14944" />
      <point x="810" y="520" timestamp="14960" />
    </stroke>
    <stroke>
      <point x="676" y="426" timestamp="15288" />
      <point x="673" y="426" timestamp="15304" />
      <point x="673" y="420" timestamp="15312" />
      <point x="673" y="420" timestamp="15320" />
      <point x="673" y="420" timestamp="15329" />
      <point x="673" y="420" timestamp="15352" />
      <point x="673" y="420" timestamp="15360" />
      <point x="673" y="420" timestamp="15376" />
      <point x="673" y="426" timestamp="15384" />
      <point x="673" y="436" timestamp="15392" />
      <point x="673" y="450" timestamp="15400" />
      <point x="666" y="463" timestamp="15416" />
      <point x="666" y="476" timestamp="15424" />
      <point x="666" y="490" timestamp="15433" />
      <point x="666" y="503" timestamp="15440" />
      <point x="666" y="516" timestamp="15456" />
      <point x="666" y="530" timestamp="15464" />
      <point x="666" y="550" timestamp="15472" />
      <point x="666" y="563" timestamp="15481" />
      <point x="666" y="570" timestamp="15496" />
      <point x="666" y="580" timestamp="15504" />
      <point x="666" y="593" timestamp="15513" />
      <point x="666" y="606" timestamp="15520" />
      <point x="666" y="613" timestamp="15536" />
      <point x="666" y="626" timestamp="15544" />
      <point x="666" y="640" timestamp="15552" />
      <point x="666" y="646" timestamp="15568" />
      <point x="666" y="660" timestamp="15576" />
      <point x="666" y="673" timestamp="15584" />
      <point x="660" y="683" timestamp="15592" />
      <point x="660" y="696" timestamp="15608" />
      <point x="660" y="710" timestamp="15616" />
      <point x="660" y="716" timestamp="15624" />
      <point x="660" y="730" timestamp="15632" />
      <point x="660" y="743" timestamp="15648" />
      <point x="660" y="750" timestamp="15656" />
      <point x="660" y="763" timestamp="15665" />
      <point x="660" y="770" timestamp="15680" />
      <point x="660" y="776" timestamp="15688" />
      <point x="660" y="780" timestamp="15697" />
      <point x="660" y="780" timestamp="15704" />
      <point x="660" y="780" timestamp="15744" />
      <point x="660" y="780" timestamp="15760" />
      <point x="660" y="780" timestamp="15768" />
      <point x="660" y="780" timestamp="15776" />
    </stroke>
  </strokes>
</character>