<?xml version="1.0" encoding="UTF-8"?>
<character>
  <utf8>n</utf8>
  <strokes>
    <stroke>
      <point x="291" y="593" timestamp="0" />
      <point x="304" y="573" timestamp="6" />
      <point x="307" y="566" timestamp="14" />
      <point x="326" y="546" timestamp="22" />
      <point x="339" y="533" timestamp="30" />
      <point x="359" y="513" timestamp="38" />
      <point x="385" y="486" timestamp="46" />
      <point x="398" y="473" timestamp="54" />
      <point x="423" y="446" timestamp="62" />
      <point x="430" y="443" timestamp="70" />
      <point x="449" y="423" timestamp="78" />
      <point x="456" y="420" timestamp="86" />
      <point x="462" y="416" timestamp="94" />
      <point x="466" y="413" timestamp="102" />
      <point x="472" y="410" timestamp="110" />
      <point x="475" y="410" timestamp="118" />
      <point x="478" y="413" timestamp="142" />
      <point x="478" y="416" timestamp="150" />
      <point x="478" y="420" timestamp="158" />
      <point x="478" y="423" timestamp="166" />
      <point x="485" y="443" timestamp="174" />
      <point x="485" y="446" timestamp="182" />
      <point x="485" y="473" timestamp="190" />
      <point x="485" y="480" timestamp="198" />
      <point x="491" y="506" timestamp="206" />
      <point x="491" y="513" timestamp="214" />
      <point x="491" y="540" timestamp="222" />
      <point x="491" y="546" timestamp="230" />
      <point x="485" y="573" timestamp="238" />
      <point x="485" y="600" timestamp="246" />
      <point x="472" y="613" timestamp="254" />
      <point x="466" y="633" timestamp="262" />
      <point x="462" y="640" timestamp="270" />
      <point x="462" y="646" timestamp="278" />
      <point x="459" y="653" timestamp="286" />
      <point x="456" y="656" timestamp="294" />
      <point x="456" y="660" timestamp="310" />
      <point x="456" y="656" timestamp="382" />
      <point x="456" y="653" timestamp="390" />
      <point x="456" y="650" timestamp="398" />
      <point x="456" y="640" timestamp="406" />
      <point x="459" y="633" timestamp="414" />
      <point x="472" y="606" timestamp="422" />
      <point x="478" y="586" timestamp="430" />
      <point x="491" y="560" timestamp="438" />
      <point x="517" y="526" timestamp="446" />
      <point x="530" y="506" timestamp="454" />
      <point x="556" y="480" timestamp="462" />
      <point x="576" y="460" timestamp="470" />
      <point x="601" y="433" timestamp="478" />
      <point x="621" y="426" timestamp="486" />
      <point x="640" y="406" timestamp="494" />
      <point x="660" y="393" timestamp="502" />
      <point x="666" y="390" timestamp="510" />
      <point x="673" y="386" timestamp="518" />
      <point x="676" y="386" timestamp="526" />
      <point x="679" y="386" timestamp="534" />
      <point x="679" y="390" timestamp="558" />
      <point x="682" y="393" timestamp="566" />
      <point x="682" y="396" timestamp="574" />
      <point x="682" y="400" timestamp="582" />
      <point x="689" y="420" timestamp="590" />
      <point x="689" y="423" timestamp="598" />
      <point x="695" y="443" timestamp="606" />
      <point x="699" y="450" timestamp="614" />
      <point x="699" y="460" timestamp="622" />
      <point x="699" y="486" timestamp="630" />
      <point x="699" y="490" timestamp="638" />
      <point x="699" y="523" timestamp="646" />
      <point x="699" y="530" timestamp="654" />
      <point x="699" y="563" timestamp="662" />
      <point x="699" y="570" timestamp="670" />
      <point x="699" y="603" timestamp="678" />
      <point x="699" y="610" timestamp="686" />
      <point x="699" y="620" timestamp="694" />
      <point x="699" y="626" timestamp="702" />
      <point x="699" y="630" timestamp="710" />
      <point x="699" y="633" timestamp="718" />
      <point x="699" y="636" timestamp="726" />
    </stroke>
  </strokes>
</character>