<?xml version="1.0" encoding="UTF-8"?>
<character>
  <utf8>y</utf8>
  <strokes>
    <stroke>
      <point x="284" y="400" timestamp="0" />
      <point x="284" y="403" timestamp="6" />
      <point x="284" y="406" timestamp="14" />
      <point x="284" y="416" timestamp="22" />
      <point x="284" y="423" timestamp="30" />
      <point x="291" y="443" timestamp="38" />
      <point x="297" y="446" timestamp="46" />
      <point x="304" y="473" timestamp="54" />
      <point x="310" y="493" timestamp="62" />
      <point x="313" y="500" timestamp="70" />
      <point x="326" y="520" timestamp="78" />
      <point x="330" y="523" timestamp="86" />
      <point x="343" y="536" timestamp="94" />
      <point x="346" y="543" timestamp="102" />
      <point x="352" y="546" timestamp="110" />
      <point x="359" y="550" timestamp="118" />
      <point x="365" y="550" timestamp="126" />
      <point x="372" y="550" timestamp="134" />
      <point x="378" y="550" timestamp="142" />
      <point x="404" y="543" timestamp="150" />
      <point x="407" y="540" timestamp="158" />
      <point x="433" y="520" timestamp="166" />
      <point x="436" y="516" timestamp="174" />
      <point x="462" y="496" timestamp="182" />
      <point x="488" y="463" timestamp="190" />
      <point x="501" y="450" timestamp="198" />
      <point x="527" y="410" timestamp="206" />
      <point x="540" y="396" timestamp="214" />
      <point x="559" y="370" timestamp="222" />
      <point x="559" y="363" timestamp="230" />
      <point x="566" y="343" timestamp="238" />
      <point x="569" y="336" timestamp="246" />
      <point x="569" y="330" timestamp="254" />
      <point x="569" y="323" timestamp="262" />
      <point x="569" y="320" timestamp="270" />
      <point x="569" y="323" timestamp="318" />
      <point x="569" y="330" timestamp="326" />
      <point x="569" y="333" timestamp="334" />
      <point x="569" y="340" timestamp="342" />
      <point x="569" y="373" timestamp="350" />
      <point x="569" y="380" timestamp="358" />
      <point x="569" y="413" timestamp="366" />
      <point x="569" y="440" timestamp="374" />
      <point x="569" y="473" timestamp="382" />
      <point x="569" y="520" timestamp="390" />
      <point x="569" y="530" timestamp="398" />
      <point x="569" y="570" timestamp="406" />
      <point x="569" y="580" timestamp="414" />
      <point x="569" y="620" timestamp="422" />
      <point x="569" y="626" timestamp="430" />
      <point x="569" y="666" timestamp="438" />
      <point x="569" y="700" timestamp="446" />
      <point x="566" y="706" timestamp="454" />
      <point x="559" y="740" timestamp="462" />
      <point x="556" y="746" timestamp="470" />
      <point x="537" y="766" timestamp="478" />
      <point x="533" y="773" timestamp="486" />
      <point x="521" y="793" timestamp="494" />
      <point x="514" y="793" timestamp="502" />
      <point x="495" y="806" timestamp="510" />
      <point x="469" y="813" timestamp="518" />
      <point x="466" y="813" timestamp="526" />
      <point x="440" y="813" timestamp="534" />
      <point x="436" y="813" timestamp="542" />
      <point x="430" y="813" timestamp="550" />
      <point x="423" y="813" timestamp="558" />
      <point x="417" y="810" timestamp="566" />
      <point x="411" y="806" timestamp="574" />
      <point x="407" y="803" timestamp="582" />
      <point x="404" y="800" timestamp="590" />
      <point x="401" y="800" timestamp="598" />
      <point x="401" y="796" timestamp="606" />
      <point x="398" y="790" timestamp="614" />
      <point x="394" y="786" timestamp="622" />
      <point x="394" y="783" timestamp="630" />
      <point x="394" y="776" timestamp="638" />
      <point x="394" y="766" timestamp="646" />
      <point x="394" y="760" timestamp="654" />
      <point x="407" y="740" timestamp="662" />
      <point x="411" y="733" timestamp="670" />
      <point x="414" y="726" timestamp="678" />
      <point x="427" y="713" timestamp="686" />
      <point x="453" y="680" timestamp="694" />
      <point x="485" y="653" timestamp="702" />
      <point x="504" y="633" timestamp="710" />
      <point x="550" y="606" timestamp="718" />
      <point x="569" y="593" timestamp="726" />
      <point x="614" y="566" timestamp="734" />
      <point x="634" y="553" timestamp="742" />
      <point x="660" y="533" timestamp="750" />
      <point x="666" y="530" timestamp="758" />
      <point x="679" y="516" timestamp="766" />
      <point x="686" y="513" timestamp="774" />
      <point x="689" y="510" timestamp="782" />
      <point x="692" y="506" timestamp="790" />
      <point x="692" y="503" timestamp="798" />
    </stroke>
  </strokes>
</character>