<?xml version="1.0" encoding="UTF-8"?>
<character>
  <utf8>g</utf8>
  <strokes>
    <stroke>
      <point x="459" y="400" timestamp="0" />
      <point x="449" y="400" timestamp="6" />
      <point x="446" y="400" timestamp="14" />
      <point x="440" y="403" timestamp="22" />
      <point x="420" y="416" timestamp="30" />
      <point x="417" y="420" timestamp="38" />
      <point x="404" y="433" timestamp="46" />
      <point x="401" y="436" timestamp="54" />
      <point x="398" y="443" timestamp="62" />
      <point x="394" y="446" timestamp="70" />
      <point x="394" y="453" timestamp="78" />
      <point x="391" y="456" timestamp="86" />
      <point x="391" y="463" timestamp="94" />
      <point x="388" y="466" timestamp="102" />
      <point x="388" y="470" timestamp="110" />
      <point x="388" y="476" timestamp="118" />
      <point x="388" y="483" timestamp="126" />
      <point x="388" y="493" timestamp="134" />
      <point x="391" y="496" timestamp="142" />
      <point x="391" y="503" timestamp="150" />
      <point x="391" y="510" timestamp="158" />
      <point x="391" y="516" timestamp="166" />
      <point x="391" y="526" timestamp="174" />
      <point x="394" y="530" timestamp="182" />
      <point x="401" y="550" timestamp="190" />
      <point x="404" y="553" timestamp="198" />
      <point x="407" y="560" timestamp="206" />
      <point x="411" y="563" timestamp="214" />
      <point x="423" y="576" timestamp="222" />
      <point x="427" y="580" timestamp="230" />
      <point x="433" y="580" timestamp="238" />
      <point x="440" y="583" timestamp="246" />
      <point x="440" y="586" timestamp="254" />
      <point x="446" y="586" timestamp="262" />
      <point x="453" y="586" timestamp="270" />
      <point x="456" y="590" timestamp="278" />
      <point x="459" y="590" timestamp="286" />
      <point x="469" y="590" timestamp="294" />
      <point x="475" y="590" timestamp="302" />
      <point x="478" y="590" timestamp="310" />
      <point x="485" y="590" timestamp="318" />
      <point x="491" y="590" timestamp="325" />
      <point x="495" y="590" timestamp="334" />
      <point x="498" y="590" timestamp="342" />
      <point x="504" y="590" timestamp="350" />
      <point x="511" y="590" timestamp="358" />
      <point x="514" y="586" timestamp="366" />
      <point x="517" y="583" timestamp="374" />
      <point x="521" y="583" timestamp="382" />
      <point x="533" y="570" timestamp="390" />
      <point x="537" y="566" timestamp="398" />
      <point x="540" y="566" timestamp="406" />
      <point x="540" y="563" timestamp="414" />
      <point x="553" y="550" timestamp="422" />
      <point x="553" y="546" timestamp="430" />
      <point x="556" y="543" timestamp="438" />
      <point x="569" y="530" timestamp="446" />
      <point x="569" y="526" timestamp="454" />
      <point x="569" y="523" timestamp="462" />
      <point x="572" y="516" timestamp="470" />
      <point x="576" y="510" timestamp="478" />
      <point x="579" y="506" timestamp="486" />
      <point x="579" y="500" timestamp="494" />
      <point x="582" y="493" timestamp="502" />
      <point x="582" y="490" timestamp="510" />
      <point x="582" y="483" timestamp="518" />
      <point x="582" y="480" timestamp="526" />
      <point x="582" y="473" timestamp="534" />
      <point x="582" y="470" timestamp="542" />
      <point x="582" y="463" timestamp="550" />
      <point x="582" y="456" timestamp="558" />
      <point x="582" y="453" timestamp="566" />
      <point x="579" y="450" timestamp="574" />
      <point x="576" y="446" timestamp="590" />
      <point x="572" y="446" timestamp="614" />
      <point x="569" y="446" timestamp="622" />
      <point x="566" y="446" timestamp="630" />
      <point x="563" y="446" timestamp="638" />
      <point x="559" y="443" timestamp="646" />
      <point x="556" y="443" timestamp="654" />
      <point x="546" y="443" timestamp="662" />
      <point x="543" y="443" timestamp="670" />
      <point x="537" y="440" timestamp="678" />
      <point x="530" y="440" timestamp="686" />
      <point x="527" y="440" timestamp="694" />
      <point x="524" y="436" timestamp="702" />
      <point x="521" y="436" timestamp="710" />
      <point x="517" y="433" timestamp="718" />
      <point x="514" y="433" timestamp="726" />
      <point x="511" y="430" timestamp="734" />
      <point x="508" y="430" timestamp="742" />
      <point x="504" y="430" timestamp="750" />
      <point x="501" y="430" timestamp="758" />
      <point x="498" y="430" timestamp="766" />
      <point x="495" y="430" timestamp="774" />
      <point x="491" y="430" timestamp="814" />
      <point x="488" y="430" timestamp="838" />
      <point x="482" y="430" timestamp="846" />
      <point x="478" y="430" timestamp="854" />
      <point x="475" y="430" timestamp="862" />
      <point x="472" y="430" timestamp="870" />
      <point x="469" y="430" timestamp="878" />
      <point x="462" y="430" timestamp="886" />
      <point x="459" y="430" timestamp="894" />
      <point x="456" y="430" timestamp="902" />
    </stroke>
    <stroke>
      <point x="582" y="480" timestamp="1536" />
      <point x="582" y="483" timestamp="1542" />
      <point x="582" y="486" timestamp="1550" />
      <point x="582" y="493" timestamp="1558" />
      <point x="582" y="496" timestamp="1566" />
      <point x="582" y="503" timestamp="1574" />
      <point x="582" y="506" timestamp="1582" />
      <point x="582" y="533" timestamp="1590" />
      <point x="582" y="540" timestamp="1598" />
      <point x="582" y="546" timestamp="1606" />
      <point x="582" y="556" timestamp="1614" />
      <point x="585" y="560" timestamp="1622" />
      <point x="585" y="570" timestamp="1630" />
      <point x="585" y="576" timestamp="1638" />
      <point x="592" y="596" timestamp="1646" />
      <point x="592" y="606" timestamp="1654" />
      <point x="595" y="610" timestamp="1662" />
      <point x="595" y="620" timestamp="1670" />
      <point x="595" y="626" timestamp="1678" />
      <point x="601" y="646" timestamp="1686" />
      <point x="601" y="650" timestamp="1694" />
      <point x="601" y="660" timestamp="1702" />
      <point x="601" y="663" timestamp="1710" />
      <point x="595" y="683" timestamp="1718" />
      <point x="595" y="693" timestamp="1726" />
      <point x="592" y="696" timestamp="1734" />
      <point x="592" y="703" timestamp="1742" />
      <point x="592" y="710" timestamp="1750" />
      <point x="585" y="730" timestamp="1758" />
      <point x="585" y="733" timestamp="1766" />
      <point x="585" y="743" timestamp="1774" />
      <point x="582" y="750" timestamp="1782" />
      <point x="582" y="753" timestamp="1790" />
      <point x="569" y="766" timestamp="1798" />
      <point x="569" y="770" timestamp="1806" />
      <point x="566" y="773" timestamp="1814" />
      <point x="566" y="776" timestamp="1822" />
      <point x="563" y="780" timestamp="1830" />
      <point x="559" y="783" timestamp="1838" />
      <point x="559" y="786" timestamp="1846" />
      <point x="556" y="790" timestamp="1854" />
      <point x="553" y="793" timestamp="1862" />
      <point x="550" y="800" timestamp="1870" />
      <point x="550" y="803" timestamp="1878" />
      <point x="546" y="810" timestamp="1886" />
      <point x="543" y="813" timestamp="1894" />
      <point x="540" y="820" timestamp="1902" />
      <point x="537" y="823" timestamp="1910" />
      <point x="533" y="826" timestamp="1918" />
      <point x="530" y="830" timestamp="1926" />
      <point x="527" y="833" timestamp="1934" />
      <point x="524" y="833" timestamp="1950" />
      <point x="521" y="836" timestamp="1958" />
      <point x="517" y="836" timestamp="1966" />
      <point x="514" y="836" timestamp="1982" />
      <point x="511" y="836" timestamp="1990" />
      <point x="508" y="836" timestamp="1998" />
      <point x="504" y="836" timestamp="2006" />
      <point x="498" y="836" timestamp="2014" />
      <point x="495" y="836" timestamp="2022" />
      <point x="491" y="836" timestamp="2030" />
      <point x="485" y="833" timestamp="2038" />
      <point x="485" y="830" timestamp="2046" />
      <point x="478" y="826" timestamp="2054" />
      <point x="478" y="823" timestamp="2062" />
      <point x="472" y="820" timestamp="2070" />
      <point x="472" y="816" timestamp="2078" />
      <point x="469" y="816" timestamp="2086" />
      <point x="469" y="813" timestamp="2094" />
      <point x="469" y="810" timestamp="2102" />
      <point x="462" y="806" timestamp="2110" />
      <point x="462" y="803" timestamp="2118" />
      <point x="462" y="796" timestamp="2126" />
      <point x="462" y="793" timestamp="2134" />
      <point x="462" y="783" timestamp="2142" />
      <point x="462" y="780" timestamp="2150" />
      <point x="462" y="773" timestamp="2158" />
      <point x="462" y="770" timestamp="2166" />
      <point x="466" y="763" timestamp="2174" />
      <point x="478" y="750" timestamp="2182" />
      <point x="482" y="746" timestamp="2190" />
      <point x="485" y="740" timestamp="2198" />
      <point x="498" y="726" timestamp="2206" />
      <point x="501" y="723" timestamp="2214" />
      <point x="504" y="720" timestamp="2222" />
      <point x="504" y="716" timestamp="2230" />
      <point x="517" y="703" timestamp="2238" />
      <point x="521" y="703" timestamp="2246" />
      <point x="533" y="690" timestamp="2254" />
      <point x="537" y="690" timestamp="2262" />
      <point x="540" y="686" timestamp="2270" />
      <point x="546" y="683" timestamp="2278" />
      <point x="553" y="680" timestamp="2286" />
      <point x="559" y="676" timestamp="2294" />
      <point x="559" y="673" timestamp="2302" />
      <point x="579" y="666" timestamp="2310" />
      <point x="582" y="663" timestamp="2318" />
      <point x="601" y="650" timestamp="2325" />
      <point x="605" y="646" timestamp="2334" />
      <point x="624" y="626" timestamp="2342" />
      <point x="627" y="626" timestamp="2350" />
      <point x="647" y="613" timestamp="2358" />
      <point x="666" y="600" timestamp="2366" />
      <point x="673" y="596" timestamp="2374" />
      <point x="676" y="593" timestamp="2382" />
      <point x="679" y="593" timestamp="2390" />
      <point x="692" y="580" timestamp="2398" />
      <point x="695" y="580" timestamp="2406" />
      <point x="699" y="576" timestamp="2414" />
      <point x="702" y="573" timestamp="2438" />
      <point x="705" y="570" timestamp="2446" />
      <point x="708" y="566" timestamp="2478" />
    </stroke>
  </strokes>
</character>