<?xml version="1.0" encoding="UTF-8"?>
<character>
  <utf8>a</utf8>
  <strokes>
    <stroke>
      <point x="543" y="333" timestamp="0" />
      <point x="540" y="333" timestamp="6" />
      <point x="540" y="330" timestamp="14" />
      <point x="537" y="330" timestamp="22" />
      <point x="533" y="330" timestamp="30" />
      <point x="514" y="323" timestamp="38" />
      <point x="495" y="316" timestamp="46" />
      <point x="491" y="316" timestamp="54" />
      <point x="472" y="303" timestamp="62" />
      <point x="466" y="303" timestamp="70" />
      <point x="433" y="303" timestamp="78" />
      <point x="427" y="300" timestamp="86" />
      <point x="401" y="300" timestamp="94" />
      <point x="394" y="300" timestamp="102" />
      <point x="368" y="300" timestamp="110" />
      <point x="336" y="300" timestamp="118" />
      <point x="330" y="303" timestamp="126" />
      <point x="304" y="303" timestamp="134" />
      <point x="297" y="306" timestamp="142" />
      <point x="271" y="320" timestamp="150" />
      <point x="268" y="320" timestamp="158" />
      <point x="249" y="333" timestamp="166" />
      <point x="245" y="336" timestamp="174" />
      <point x="233" y="350" timestamp="182" />
      <point x="220" y="363" timestamp="190" />
      <point x="216" y="366" timestamp="198" />
      <point x="213" y="373" timestamp="206" />
      <point x="213" y="376" timestamp="214" />
      <point x="210" y="383" timestamp="222" />
      <point x="207" y="386" timestamp="230" />
      <point x="207" y="393" timestamp="238" />
      <point x="207" y="400" timestamp="246" />
      <point x="207" y="403" timestamp="254" />
      <point x="207" y="413" timestamp="262" />
      <point x="207" y="416" timestamp="270" />
      <point x="207" y="443" timestamp="278" />
      <point x="207" y="446" timestamp="286" />
      <point x="207" y="456" timestamp="294" />
      <point x="207" y="460" timestamp="302" />
      <point x="210" y="466" timestamp="310" />
      <point x="210" y="476" timestamp="318" />
      <point x="213" y="476" timestamp="326" />
      <point x="216" y="483" timestamp="334" />
      <point x="216" y="490" timestamp="342" />
      <point x="229" y="503" timestamp="350" />
      <point x="229" y="510" timestamp="358" />
      <point x="249" y="523" timestamp="366" />
      <point x="262" y="536" timestamp="374" />
      <point x="265" y="543" timestamp="382" />
      <point x="278" y="563" timestamp="390" />
      <point x="281" y="566" timestamp="398" />
      <point x="294" y="586" timestamp="406" />
      <point x="297" y="590" timestamp="414" />
      <point x="304" y="593" timestamp="422" />
      <point x="307" y="596" timestamp="430" />
      <point x="313" y="600" timestamp="438" />
      <point x="326" y="613" timestamp="446" />
      <point x="333" y="616" timestamp="454" />
      <point x="339" y="620" timestamp="462" />
      <point x="343" y="623" timestamp="470" />
      <point x="349" y="626" timestamp="478" />
      <point x="352" y="626" timestamp="486" />
      <point x="359" y="630" timestamp="494" />
      <point x="365" y="630" timestamp="502" />
      <point x="368" y="630" timestamp="510" />
      <point x="372" y="630" timestamp="518" />
      <point x="375" y="630" timestamp="526" />
      <point x="378" y="630" timestamp="534" />
      <point x="381" y="630" timestamp="542" />
      <point x="385" y="630" timestamp="550" />
      <point x="388" y="626" timestamp="558" />
      <point x="391" y="626" timestamp="566" />
      <point x="394" y="623" timestamp="574" />
      <point x="398" y="620" timestamp="582" />
      <point x="404" y="616" timestamp="590" />
      <point x="407" y="613" timestamp="598" />
      <point x="420" y="600" timestamp="606" />
      <point x="423" y="596" timestamp="614" />
      <point x="443" y="583" timestamp="622" />
      <point x="456" y="570" timestamp="630" />
      <point x="459" y="566" timestamp="638" />
      <point x="472" y="540" timestamp="646" />
      <point x="475" y="536" timestamp="654" />
      <point x="488" y="516" timestamp="662" />
      <point x="491" y="510" timestamp="670" />
      <point x="498" y="490" timestamp="678" />
      <point x="498" y="483" timestamp="686" />
      <point x="498" y="456" timestamp="694" />
      <point x="498" y="430" timestamp="702" />
      <point x="498" y="423" timestamp="710" />
      <point x="504" y="403" timestamp="718" />
      <point x="508" y="396" timestamp="726" />
      <point x="508" y="386" timestamp="734" />
      <point x="508" y="383" timestamp="742" />
      <point x="511" y="376" timestamp="750" />
      <point x="511" y="373" timestamp="758" />
      <point x="517" y="353" timestamp="766" />
      <point x="521" y="350" timestamp="774" />
      <point x="521" y="346" timestamp="782" />
      <point x="521" y="343" timestamp="790" />
      <point x="521" y="340" timestamp="798" />
      <point x="521" y="333" timestamp="806" />
      <point x="521" y="330" timestamp="814" />
      <point x="521" y="326" timestamp="822" />
      <point x="521" y="323" timestamp="830" />
      <point x="521" y="320" timestamp="838" />
      <point x="521" y="323" timestamp="942" />
      <point x="521" y="326" timestamp="950" />
      <point x="521" y="333" timestamp="958" />
      <point x="521" y="336" timestamp="966" />
      <point x="521" y="343" timestamp="974" />
      <point x="521" y="346" timestamp="982" />
      <point x="521" y="353" timestamp="990" />
      <point x="521" y="360" timestamp="998" />
      <point x="521" y="370" timestamp="1006" />
      <point x="521" y="376" timestamp="1014" />
      <point x="521" y="386" timestamp="1022" />
      <point x="521" y="413" timestamp="1030" />
      <point x="521" y="420" timestamp="1038" />
      <point x="521" y="446" timestamp="1046" />
      <point x="521" y="453" timestamp="1054" />
      <point x="521" y="480" timestamp="1062" />
      <point x="521" y="486" timestamp="1070" />
      <point x="521" y="513" timestamp="1078" />
      <point x="527" y="546" timestamp="1086" />
      <point x="530" y="553" timestamp="1094" />
      <point x="530" y="580" timestamp="1102" />
      <point x="533" y="583" timestamp="1110" />
      <point x="533" y="593" timestamp="1118" />
      <point x="533" y="600" timestamp="1126" />
      <point x="537" y="606" timestamp="1134" />
      <point x="540" y="610" timestamp="1142" />
      <point x="543" y="616" timestamp="1150" />
      <point x="546" y="620" timestamp="1158" />
      <point x="546" y="623" timestamp="1166" />
      <point x="553" y="626" timestamp="1174" />
      <point x="553" y="630" timestamp="1182" />
      <point x="556" y="633" timestamp="1190" />
      <point x="559" y="633" timestamp="1198" />
      <point x="563" y="640" timestamp="1206" />
      <point x="566" y="643" timestamp="1214" />
      <point x="569" y="643" timestamp="1222" />
      <point x="576" y="646" timestamp="1230" />
      <point x="576" y="650" timestamp="1238" />
      <point x="582" y="650" timestamp="1246" />
      <point x="585" y="650" timestamp="1254" />
      <point x="588" y="653" timestamp="1262" />
      <point x="592" y="653" timestamp="1270" />
      <point x="598" y="653" timestamp="1278" />
      <point x="605" y="653" timestamp="1286" />
      <point x="608" y="656" timestamp="1294" />
      <point x="614" y="656" timestamp="1302" />
      <point x="618" y="656" timestamp="1310" />
      <point x="621" y="653" timestamp="1318" />
      <point x="624" y="653" timestamp="1326" />
      <point x="624" y="650" timestamp="1334" />
    </stroke>
  </strokes>
</character>